odoo10_addon_web_searchbar_full_width-10.0.1.0.0-py2.7-nspkg.pth
odoo/addons/web_searchbar_full_width/__manifest__.py
odoo/addons/web_searchbar_full_width/__init__.py
odoo/addons/web_searchbar_full_width/README.rst
odoo/addons/web_searchbar_full_width/views/templates.xml
odoo/addons/web_searchbar_full_width/static/description/preview.png
odoo/addons/web_searchbar_full_width/static/description/icon.png
odoo/addons/web_searchbar_full_width/static/src/css/web_searchbar_full_width.css
odoo10_addon_web_searchbar_full_width-10.0.1.0.0.dist-info/top_level.txt
odoo10_addon_web_searchbar_full_width-10.0.1.0.0.dist-info/WHEEL
odoo10_addon_web_searchbar_full_width-10.0.1.0.0.dist-info/RECORD
odoo10_addon_web_searchbar_full_width-10.0.1.0.0.dist-info/metadata.json
odoo10_addon_web_searchbar_full_width-10.0.1.0.0.dist-info/DESCRIPTION.rst
odoo10_addon_web_searchbar_full_width-10.0.1.0.0.dist-info/METADATA
odoo10_addon_web_searchbar_full_width-10.0.1.0.0.dist-info/namespace_packages.txt
